tester/__init__.py
tester/tester1.py
directory_splitter-1.0.3.dist-info/METADATA
directory_splitter-1.0.3.dist-info/WHEEL
directory_splitter-1.0.3.dist-info/entry_points.txt
directory_splitter-1.0.3.dist-info/top_level.txt
directory_splitter-1.0.3.dist-info/RECORD
