Metadata-Version: 2.1
Name: directory-splitter
Version: 1.0.3
Summary: A script to split and extract unique endpoints from a list of URLs.
License: MIT
Keywords: directory-splitter url-parser
Requires-Dist: argparse
